CHANGELOG.txt
LICENSE.txt
MANIFEST.in
README.txt
setup.py
deconfounderLA.egg-info/PKG-INFO
deconfounderLA.egg-info/SOURCES.txt
deconfounderLA.egg-info/dependency_links.txt
deconfounderLA.egg-info/top_level.txt
function_library/__init__.py